pandoc_plantuml_filter_panflute/__init__.py
pandoc_plantuml_filter_panflute/__main__.py
pandoc_plantuml_filter_panflute/filter.py
pandoc_plantuml_filter_panflute-0.1.1.dist-info/entry_points.txt
pandoc_plantuml_filter_panflute-0.1.1.dist-info/LICENSE
pandoc_plantuml_filter_panflute-0.1.1.dist-info/WHEEL
pandoc_plantuml_filter_panflute-0.1.1.dist-info/METADATA
pandoc_plantuml_filter_panflute-0.1.1.dist-info/RECORD
