Metadata-Version: 2.1
Name: pandoc-plantuml-filter-panflute
Version: 0.1.1
Summary: 
License: MIT
Author: Augusto Zanellato
Author-email: augusto.zanellato@gmail.com
Requires-Python: >=3.7.2,<4.0.0
Classifier: License :: OSI Approved :: MIT License
Classifier: Programming Language :: Python :: 3
Classifier: Programming Language :: Python :: 3.8
Classifier: Programming Language :: Python :: 3.9
Classifier: Programming Language :: Python :: 3.10
Classifier: Programming Language :: Python :: 3.11
Requires-Dist: loguru (>=0.6.0,<0.7.0)
Requires-Dist: panflute (>=2.2.3,<3.0.0)
